README.txt
ooch.py
setup.py
ooch.egg-info/PKG-INFO
ooch.egg-info/SOURCES.txt
ooch.egg-info/dependency_links.txt
ooch.egg-info/requires.txt
ooch.egg-info/top_level.txt