Metadata-Version: 1.0
Name: ooch
Version: 1.0.1
Summary: python -mooch (sharing files on a LAN made kinda easy)
Home-page: http://pypi.python.org/pypi/ooch
Author: Richard Jones
Author-email: richard@mechanicalcat.net
License: UNKNOWN
Platform: UNKNOWN
Classifier: Programming Language :: Python :: 2.5
Classifier: Programming Language :: Python :: 2.6
Classifier: Programming Language :: Python :: 2.7
Classifier: License :: OSI Approved :: BSD License
